[
 {
  "id": 140486,
  "postcode": 61098,
  "number": 2,
  "suffix": "",
  "block": "",
  "streetid": 2848,
  "status_id": 1,
  "detail_type_index": 0,
  "AddressDetailType": {
   "id": 0,
   "t_ru": " ",
   "t_ukr": " "
  },
  "detail": "",
  "detail_ua": "",
  "detail_number": "",
  "source_id": 0,
  "same_adr_comm": "",
  "confrm": "",
  "reg_date": "",
  "longt": 36.1658841975,
  "lati": 49.9777255414,
  "FullNameUA": "вулиця Кашуби, 2",
  "ChildsIds": []
 },
 {
  "id": 140487,
  "postcode": 61098,
  "number": 2,
  "suffix": "/1",
  "block": "",
  "streetid": 2848,
  "status_id": 1,
  "detail_type_index": 0,
  "AddressDetailType": {
   "id": 0,
   "t_ru": " ",
   "t_ukr": " "
  },
  "detail": "",
  "detail_ua": "",
  "detail_number": "",
  "source_id": 0,
  "same_adr_comm": "",
  "confrm": "",
  "reg_date": "",
  "longt": 36.1669567279,
  "lati": 49.9781183913,
  "FullNameUA": "вулиця Кашуби, 2/1",
  "ChildsIds": []
 },
 {
  "id": 181793,
  "postcode": 61098,
  "number": 2,
  "suffix": "/1-Б",
  "block": "",
  "streetid": 2848,
  "status_id": 1,
  "detail_type_index": 0,
  "AddressDetailType": {
   "id": 0,
   "t_ru": " ",
   "t_ukr": " "
  },
  "detail": "",
  "detail_ua": "",
  "detail_number": "",
  "source_id": 0,
  "same_adr_comm": "",
  "confrm": "",
  "reg_date": "",
  "longt": 36.1672585703,
  "lati": 49.9779410021,
  "FullNameUA": "вулиця Кашуби, 2/1-Б",
  "ChildsIds": []
 },
 {
  "id": 140488,
  "postcode": 61098,
  "number": 3,
  "suffix": "",
  "block": "",
  "streetid": 2848,
  "status_id": 1,
  "detail_type_index": 0,
  "AddressDetailType": {
   "id": 0,
   "t_ru": " ",
   "t_ukr": " "
  },
  "detail": "",
  "detail_ua": "",
  "detail_number": "",
  "source_id": 0,
  "same_adr_comm": "",
  "confrm": "",
  "reg_date": "",
  "longt": 36.1651830808,
  "lati": 49.9775159772,
  "FullNameUA": "вулиця Кашуби, 3",
  "ChildsIds": []
 },
 {
  "id": 179037,
  "postcode": 61098,
  "number": 3,
  "suffix": "А",
  "block": "",
  "streetid": 2848,
  "status_id": 1,
  "detail_type_index": 0,
  "AddressDetailType": {
   "id": 0,
   "t_ru": " ",
   "t_ukr": " "
  },
  "detail": "",
  "detail_ua": "",
  "detail_number": "",
  "source_id": 0,
  "same_adr_comm": "",
  "confrm": "градархив",
  "reg_date": "",
  "longt": 36.1646034598,
  "lati": 49.977583999,
  "FullNameUA": "вулиця Кашуби, 3-А",
  "ChildsIds": []
 },
 {
  "id": 140489,
  "postcode": 61098,
  "number": 4,
  "suffix": "",
  "block": "",
  "streetid": 2848,
  "status_id": 1,
  "detail_type_index": 0,
  "AddressDetailType": {
   "id": 0,
   "t_ru": " ",
   "t_ukr": " "
  },
  "detail": "",
  "detail_ua": "",
  "detail_number": "",
  "source_id": 0,
  "same_adr_comm": "",
  "confrm": "",
  "reg_date": "",
  "longt": 36.1655588013,
  "lati": 49.9780106869,
  "FullNameUA": "вулиця Кашуби, 4",
  "ChildsIds": []
 },
 {
  "id": 140490,
  "postcode": 61098,
  "number": 5,
  "suffix": "",
  "block": "",
  "streetid": 2848,
  "status_id": 1,
  "detail_type_index": 0,
  "AddressDetailType": {
   "id": 0,
   "t_ru": " ",
   "t_ukr": " "
  },
  "detail": "",
  "detail_ua": "",
  "detail_number": "",
  "source_id": 0,
  "same_adr_comm": "",
  "confrm": "",
  "reg_date": "",
  "longt": 36.164451403,
  "lati": 49.978205888,
  "FullNameUA": "вулиця Кашуби, 5",
  "ChildsIds": []
 },
 {
  "id": 140491,
  "postcode": 61098,
  "number": 6,
  "suffix": "",
  "block": "",
  "streetid": 2848,
  "status_id": 1,
  "detail_type_index": 0,
  "AddressDetailType": {
   "id": 0,
   "t_ru": " ",
   "t_ukr": " "
  },
  "detail": "",
  "detail_ua": "",
  "detail_number": "",
  "source_id": 0,
  "same_adr_comm": "",
  "confrm": "",
  "reg_date": "",
  "longt": 36.1646601254,
  "lati": 49.9788383259,
  "FullNameUA": "вулиця Кашуби, 6",
  "ChildsIds": []
 },
 {
  "id": 140492,
  "postcode": 61098,
  "number": 7,
  "suffix": "",
  "block": "",
  "streetid": 2848,
  "status_id": 1,
  "detail_type_index": 0,
  "AddressDetailType": {
   "id": 0,
   "t_ru": " ",
   "t_ukr": " "
  },
  "detail": "",
  "detail_ua": "",
  "detail_number": "",
  "source_id": 0,
  "same_adr_comm": "",
  "confrm": "",
  "reg_date": "",
  "longt": 36.1637728663,
  "lati": 49.9788003332,
  "FullNameUA": "вулиця Кашуби, 7",
  "ChildsIds": []
 },
 {
  "id": 140493,
  "postcode": 61098,
  "number": 9,
  "suffix": "",
  "block": "",
  "streetid": 2848,
  "status_id": 1,
  "detail_type_index": 0,
  "AddressDetailType": {
   "id": 0,
   "t_ru": " ",
   "t_ukr": " "
  },
  "detail": "",
  "detail_ua": "",
  "detail_number": "",
  "source_id": 0,
  "same_adr_comm": "",
  "confrm": "",
  "reg_date": "",
  "longt": 36.1642209888,
  "lati": 49.9793265816,
  "FullNameUA": "вулиця Кашуби, 9",
  "ChildsIds": []
 },
 {
  "id": 140494,
  "postcode": 61098,
  "number": 10,
  "suffix": "",
  "block": "",
  "streetid": 2848,
  "status_id": 1,
  "detail_type_index": 0,
  "AddressDetailType": {
   "id": 0,
   "t_ru": " ",
   "t_ukr": " "
  },
  "detail": "",
  "detail_ua": "",
  "detail_number": "",
  "source_id": 0,
  "same_adr_comm": "",
  "confrm": "",
  "reg_date": "",
  "longt": 36.1636362572,
  "lati": 49.9807583856,
  "FullNameUA": "вулиця Кашуби, 10",
  "ChildsIds": []
 },
 {
  "id": 140495,
  "postcode": 61098,
  "number": 11,
  "suffix": "",
  "block": "",
  "streetid": 2848,
  "status_id": 1,
  "detail_type_index": 0,
  "AddressDetailType": {
   "id": 0,
   "t_ru": " ",
   "t_ukr": " "
  },
  "detail": "",
  "detail_ua": "",
  "detail_number": "",
  "source_id": 0,
  "same_adr_comm": "",
  "confrm": "",
  "reg_date": "",
  "longt": 36.164803419,
  "lati": 49.9795745204,
  "FullNameUA": "вулиця Кашуби, 11",
  "ChildsIds": []
 },
 {
  "id": 140496,
  "postcode": 61098,
  "number": 13,
  "suffix": "",
  "block": "",
  "streetid": 2848,
  "status_id": 1,
  "detail_type_index": 0,
  "AddressDetailType": {
   "id": 0,
   "t_ru": " ",
   "t_ukr": " "
  },
  "detail": "",
  "detail_ua": "",
  "detail_number": "",
  "source_id": 0,
  "same_adr_comm": "",
  "confrm": "",
  "reg_date": "",
  "longt": 36.1656456578,
  "lati": 49.9799253684,
  "FullNameUA": "вулиця Кашуби, 13",
  "ChildsIds": []
 }
]