[
 {
  "id": 181601,
  "postcode": 61067,
  "number": 1,
  "suffix": "В",
  "block": "",
  "streetid": 3771,
  "status_id": 1,
  "detail_type_index": 0,
  "AddressDetailType": {
   "id": 0,
   "t_ru": " ",
   "t_ukr": " "
  },
  "detail": "",
  "detail_ua": "",
  "detail_number": "",
  "source_id": 0,
  "same_adr_comm": "",
  "confrm": "",
  "reg_date": "",
  "longt": 36.175034353,
  "lati": 50.0097481467,
  "FullNameUA": "вулиця Рельєфна, 1-В",
  "ChildsIds": []
 },
 {
  "id": 181600,
  "postcode": 61067,
  "number": 1,
  "suffix": "Б",
  "block": "",
  "streetid": 3771,
  "status_id": 1,
  "detail_type_index": 0,
  "AddressDetailType": {
   "id": 0,
   "t_ru": " ",
   "t_ukr": " "
  },
  "detail": "",
  "detail_ua": "",
  "detail_number": "",
  "source_id": 0,
  "same_adr_comm": "",
  "confrm": "",
  "reg_date": "",
  "longt": 36.1745259224,
  "lati": 50.0101004868,
  "FullNameUA": "вулиця Рельєфна, 1-Б",
  "ChildsIds": []
 },
 {
  "id": 181580,
  "postcode": 61067,
  "number": 1,
  "suffix": "Г",
  "block": "",
  "streetid": 3771,
  "status_id": 1,
  "detail_type_index": 0,
  "AddressDetailType": {
   "id": 0,
   "t_ru": " ",
   "t_ukr": " "
  },
  "detail": "",
  "detail_ua": "",
  "detail_number": "",
  "source_id": 1,
  "same_adr_comm": "житловий будинок літ. \"А-1\"",
  "confrm": "",
  "reg_date": "04.11.2019 16:16:25",
  "longt": 36.1733752346,
  "lati": 50.0107035185,
  "FullNameUA": "вулиця Рельєфна, 1-Г",
  "ChildsIds": []
 },
 {
  "id": 143866,
  "postcode": 61067,
  "number": 1,
  "suffix": "",
  "block": "",
  "streetid": 3771,
  "status_id": 1,
  "detail_type_index": 0,
  "AddressDetailType": {
   "id": 0,
   "t_ru": " ",
   "t_ukr": " "
  },
  "detail": "",
  "detail_ua": "",
  "detail_number": "",
  "source_id": 0,
  "same_adr_comm": "",
  "confrm": "",
  "reg_date": "",
  "longt": 36.1735178208,
  "lati": 50.0106172053,
  "FullNameUA": "вулиця Рельєфна, 1",
  "ChildsIds": []
 },
 {
  "id": 143867,
  "postcode": 61067,
  "number": 1,
  "suffix": "А",
  "block": "",
  "streetid": 3771,
  "status_id": 1,
  "detail_type_index": 0,
  "AddressDetailType": {
   "id": 0,
   "t_ru": " ",
   "t_ukr": " "
  },
  "detail": "",
  "detail_ua": "",
  "detail_number": "",
  "source_id": 0,
  "same_adr_comm": "",
  "confrm": "",
  "reg_date": "",
  "longt": 36.1740013335,
  "lati": 50.0103186779,
  "FullNameUA": "вулиця Рельєфна, 1-А",
  "ChildsIds": []
 },
 {
  "id": 143869,
  "postcode": 61067,
  "number": 2,
  "suffix": "А",
  "block": "",
  "streetid": 3771,
  "status_id": 1,
  "detail_type_index": 0,
  "AddressDetailType": {
   "id": 0,
   "t_ru": " ",
   "t_ukr": " "
  },
  "detail": "",
  "detail_ua": "",
  "detail_number": "",
  "source_id": 0,
  "same_adr_comm": "",
  "confrm": "",
  "reg_date": "",
  "longt": 36.1760499556,
  "lati": 50.0097842676,
  "FullNameUA": "вулиця Рельєфна, 2-А",
  "ChildsIds": []
 },
 {
  "id": 143868,
  "postcode": 61067,
  "number": 2,
  "suffix": "",
  "block": "",
  "streetid": 3771,
  "status_id": 1,
  "detail_type_index": 0,
  "AddressDetailType": {
   "id": 0,
   "t_ru": " ",
   "t_ukr": " "
  },
  "detail": "",
  "detail_ua": "",
  "detail_number": "",
  "source_id": 0,
  "same_adr_comm": "",
  "confrm": "",
  "reg_date": "",
  "longt": 36.1757784875,
  "lati": 50.0099144021,
  "FullNameUA": "вулиця Рельєфна, 2",
  "ChildsIds": []
 },
 {
  "id": 143870,
  "postcode": 61067,
  "number": 3,
  "suffix": "",
  "block": "",
  "streetid": 3771,
  "status_id": 1,
  "detail_type_index": 0,
  "AddressDetailType": {
   "id": 0,
   "t_ru": " ",
   "t_ukr": " "
  },
  "detail": "",
  "detail_ua": "",
  "detail_number": "",
  "source_id": 0,
  "same_adr_comm": "",
  "confrm": "",
  "reg_date": "",
  "longt": 36.1731488082,
  "lati": 50.0107916419,
  "FullNameUA": "вулиця Рельєфна, 3",
  "ChildsIds": []
 },
 {
  "id": 143871,
  "postcode": 61067,
  "number": 4,
  "suffix": "",
  "block": "",
  "streetid": 3771,
  "status_id": 1,
  "detail_type_index": 0,
  "AddressDetailType": {
   "id": 0,
   "t_ru": " ",
   "t_ukr": " "
  },
  "detail": "",
  "detail_ua": "",
  "detail_number": "",
  "source_id": 0,
  "same_adr_comm": "",
  "confrm": "",
  "reg_date": "",
  "longt": 36.1755469946,
  "lati": 50.0100434877,
  "FullNameUA": "вулиця Рельєфна, 4",
  "ChildsIds": []
 },
 {
  "id": 143873,
  "postcode": 61067,
  "number": 5,
  "suffix": "А",
  "block": "",
  "streetid": 3771,
  "status_id": 1,
  "detail_type_index": 0,
  "AddressDetailType": {
   "id": 0,
   "t_ru": " ",
   "t_ukr": " "
  },
  "detail": "",
  "detail_ua": "",
  "detail_number": "",
  "source_id": 0,
  "same_adr_comm": "",
  "confrm": "",
  "reg_date": "",
  "longt": 36.1728087254,
  "lati": 50.010763358,
  "FullNameUA": "вулиця Рельєфна, 5-А",
  "ChildsIds": []
 },
 {
  "id": 143872,
  "postcode": 61067,
  "number": 5,
  "suffix": "",
  "block": "",
  "streetid": 3771,
  "status_id": 1,
  "detail_type_index": 0,
  "AddressDetailType": {
   "id": 0,
   "t_ru": " ",
   "t_ukr": " "
  },
  "detail": "",
  "detail_ua": "",
  "detail_number": "",
  "source_id": 0,
  "same_adr_comm": "",
  "confrm": "",
  "reg_date": "",
  "longt": 36.1728877219,
  "lati": 50.0109332402,
  "FullNameUA": "вулиця Рельєфна, 5",
  "ChildsIds": []
 },
 {
  "id": 143874,
  "postcode": 61067,
  "number": 6,
  "suffix": "",
  "block": "",
  "streetid": 3771,
  "status_id": 1,
  "detail_type_index": 0,
  "AddressDetailType": {
   "id": 0,
   "t_ru": " ",
   "t_ukr": " "
  },
  "detail": "",
  "detail_ua": "",
  "detail_number": "",
  "source_id": 0,
  "same_adr_comm": "",
  "confrm": "",
  "reg_date": "",
  "longt": 36.1752832328,
  "lati": 50.0101749669,
  "FullNameUA": "вулиця Рельєфна, 6",
  "ChildsIds": []
 },
 {
  "id": 143875,
  "postcode": 61067,
  "number": 7,
  "suffix": "",
  "block": "",
  "streetid": 3771,
  "status_id": 1,
  "detail_type_index": 0,
  "AddressDetailType": {
   "id": 0,
   "t_ru": " ",
   "t_ukr": " "
  },
  "detail": "",
  "detail_ua": "",
  "detail_number": "",
  "source_id": 0,
  "same_adr_comm": "",
  "confrm": "",
  "reg_date": "",
  "longt": 36.1726335936,
  "lati": 50.0110389827,
  "FullNameUA": "вулиця Рельєфна, 7",
  "ChildsIds": []
 },
 {
  "id": 143876,
  "postcode": 61067,
  "number": 8,
  "suffix": "",
  "block": "",
  "streetid": 3771,
  "status_id": 1,
  "detail_type_index": 0,
  "AddressDetailType": {
   "id": 0,
   "t_ru": " ",
   "t_ukr": " "
  },
  "detail": "",
  "detail_ua": "",
  "detail_number": "",
  "source_id": 0,
  "same_adr_comm": "",
  "confrm": "",
  "reg_date": "",
  "longt": 36.1749643878,
  "lati": 50.0102333355,
  "FullNameUA": "вулиця Рельєфна, 8",
  "ChildsIds": []
 },
 {
  "id": 143877,
  "postcode": 61067,
  "number": 9,
  "suffix": "",
  "block": "",
  "streetid": 3771,
  "status_id": 1,
  "detail_type_index": 0,
  "AddressDetailType": {
   "id": 0,
   "t_ru": " ",
   "t_ukr": " "
  },
  "detail": "",
  "detail_ua": "",
  "detail_number": "",
  "source_id": 0,
  "same_adr_comm": "",
  "confrm": "",
  "reg_date": "",
  "longt": 36.1724095238,
  "lati": 50.0111504175,
  "FullNameUA": "вулиця Рельєфна, 9",
  "ChildsIds": []
 },
 {
  "id": 143878,
  "postcode": 61067,
  "number": 10,
  "suffix": "",
  "block": "",
  "streetid": 3771,
  "status_id": 1,
  "detail_type_index": 0,
  "AddressDetailType": {
   "id": 0,
   "t_ru": " ",
   "t_ukr": " "
  },
  "detail": "",
  "detail_ua": "",
  "detail_number": "",
  "source_id": 0,
  "same_adr_comm": "",
  "confrm": "",
  "reg_date": "",
  "longt": 36.1748141454,
  "lati": 50.0104307201,
  "FullNameUA": "вулиця Рельєфна, 10",
  "ChildsIds": []
 },
 {
  "id": 143879,
  "postcode": 61067,
  "number": 11,
  "suffix": "",
  "block": "",
  "streetid": 3771,
  "status_id": 1,
  "detail_type_index": 0,
  "AddressDetailType": {
   "id": 0,
   "t_ru": " ",
   "t_ukr": " "
  },
  "detail": "",
  "detail_ua": "",
  "detail_number": "",
  "source_id": 0,
  "same_adr_comm": "",
  "confrm": "",
  "reg_date": "",
  "longt": 36.1721752117,
  "lati": 50.0112756101,
  "FullNameUA": "вулиця Рельєфна, 11",
  "ChildsIds": []
 },
 {
  "id": 143880,
  "postcode": 61067,
  "number": 12,
  "suffix": "",
  "block": "",
  "streetid": 3771,
  "status_id": 1,
  "detail_type_index": 0,
  "AddressDetailType": {
   "id": 0,
   "t_ru": " ",
   "t_ukr": " "
  },
  "detail": "",
  "detail_ua": "",
  "detail_number": "",
  "source_id": 0,
  "same_adr_comm": "",
  "confrm": "",
  "reg_date": "",
  "longt": 36.174683174,
  "lati": 50.0104773785,
  "FullNameUA": "вулиця Рельєфна, 12",
  "ChildsIds": []
 },
 {
  "id": 143881,
  "postcode": 61067,
  "number": 13,
  "suffix": "",
  "block": "",
  "streetid": 3771,
  "status_id": 1,
  "detail_type_index": 0,
  "AddressDetailType": {
   "id": 0,
   "t_ru": " ",
   "t_ukr": " "
  },
  "detail": "",
  "detail_ua": "",
  "detail_number": "",
  "source_id": 0,
  "same_adr_comm": "",
  "confrm": "",
  "reg_date": "",
  "longt": 36.1719393554,
  "lati": 50.0113955537,
  "FullNameUA": "вулиця Рельєфна, 13",
  "ChildsIds": []
 },
 {
  "id": 143882,
  "postcode": 61067,
  "number": 14,
  "suffix": "",
  "block": "",
  "streetid": 3771,
  "status_id": 1,
  "detail_type_index": 0,
  "AddressDetailType": {
   "id": 0,
   "t_ru": " ",
   "t_ukr": " "
  },
  "detail": "",
  "detail_ua": "",
  "detail_number": "",
  "source_id": 0,
  "same_adr_comm": "",
  "confrm": "",
  "reg_date": "",
  "longt": 36.1744048463,
  "lati": 50.0104656367,
  "FullNameUA": "вулиця Рельєфна, 14",
  "ChildsIds": []
 },
 {
  "id": 143883,
  "postcode": 61067,
  "number": 15,
  "suffix": "",
  "block": "",
  "streetid": 3771,
  "status_id": 1,
  "detail_type_index": 0,
  "AddressDetailType": {
   "id": 0,
   "t_ru": " ",
   "t_ukr": " "
  },
  "detail": "",
  "detail_ua": "",
  "detail_number": "",
  "source_id": 0,
  "same_adr_comm": "",
  "confrm": "",
  "reg_date": "",
  "longt": 36.171657401,
  "lati": 50.0114637159,
  "FullNameUA": "вулиця Рельєфна, 15",
  "ChildsIds": []
 },
 {
  "id": 143884,
  "postcode": 61067,
  "number": 16,
  "suffix": "",
  "block": "",
  "streetid": 3771,
  "status_id": 1,
  "detail_type_index": 0,
  "AddressDetailType": {
   "id": 0,
   "t_ru": " ",
   "t_ukr": " "
  },
  "detail": "",
  "detail_ua": "",
  "detail_number": "",
  "source_id": 0,
  "same_adr_comm": "",
  "confrm": "",
  "reg_date": "",
  "longt": 36.1745099691,
  "lati": 50.0107563668,
  "FullNameUA": "вулиця Рельєфна, 16",
  "ChildsIds": []
 },
 {
  "id": 143885,
  "postcode": 61067,
  "number": 17,
  "suffix": "",
  "block": "",
  "streetid": 3771,
  "status_id": 1,
  "detail_type_index": 0,
  "AddressDetailType": {
   "id": 0,
   "t_ru": " ",
   "t_ukr": " "
  },
  "detail": "",
  "detail_ua": "",
  "detail_number": "",
  "source_id": 0,
  "same_adr_comm": "",
  "confrm": "",
  "reg_date": "",
  "longt": 36.1714517393,
  "lati": 50.0116220821,
  "FullNameUA": "вулиця Рельєфна, 17",
  "ChildsIds": []
 },
 {
  "id": 143886,
  "postcode": 61067,
  "number": 18,
  "suffix": "",
  "block": "",
  "streetid": 3771,
  "status_id": 1,
  "detail_type_index": 0,
  "AddressDetailType": {
   "id": 0,
   "t_ru": " ",
   "t_ukr": " "
  },
  "detail": "",
  "detail_ua": "",
  "detail_number": "",
  "source_id": 0,
  "same_adr_comm": "",
  "confrm": "",
  "reg_date": "",
  "longt": 36.1741827315,
  "lati": 50.0107356379,
  "FullNameUA": "вулиця Рельєфна, 18",
  "ChildsIds": []
 },
 {
  "id": 143887,
  "postcode": 61067,
  "number": 19,
  "suffix": "",
  "block": "",
  "streetid": 3771,
  "status_id": 1,
  "detail_type_index": 0,
  "AddressDetailType": {
   "id": 0,
   "t_ru": " ",
   "t_ukr": " "
  },
  "detail": "",
  "detail_ua": "",
  "detail_number": "",
  "source_id": 0,
  "same_adr_comm": "",
  "confrm": "",
  "reg_date": "",
  "longt": 36.1712460137,
  "lati": 50.0117007804,
  "FullNameUA": "вулиця Рельєфна, 19",
  "ChildsIds": []
 },
 {
  "id": 143888,
  "postcode": 61067,
  "number": 20,
  "suffix": "",
  "block": "",
  "streetid": 3771,
  "status_id": 1,
  "detail_type_index": 0,
  "AddressDetailType": {
   "id": 0,
   "t_ru": " ",
   "t_ukr": " "
  },
  "detail": "",
  "detail_ua": "",
  "detail_number": "",
  "source_id": 0,
  "same_adr_comm": "",
  "confrm": "",
  "reg_date": "",
  "longt": 36.1739083377,
  "lati": 50.01072899,
  "FullNameUA": "вулиця Рельєфна, 20",
  "ChildsIds": []
 },
 {
  "id": 143889,
  "postcode": 61067,
  "number": 21,
  "suffix": "",
  "block": "",
  "streetid": 3771,
  "status_id": 1,
  "detail_type_index": 0,
  "AddressDetailType": {
   "id": 0,
   "t_ru": " ",
   "t_ukr": " "
  },
  "detail": "",
  "detail_ua": "",
  "detail_number": "",
  "source_id": 0,
  "same_adr_comm": "",
  "confrm": "",
  "reg_date": "",
  "longt": 36.1709402332,
  "lati": 50.0118554802,
  "FullNameUA": "вулиця Рельєфна, 21",
  "ChildsIds": []
 },
 {
  "id": 143890,
  "postcode": 61067,
  "number": 22,
  "suffix": "",
  "block": "",
  "streetid": 3771,
  "status_id": 1,
  "detail_type_index": 0,
  "AddressDetailType": {
   "id": 0,
   "t_ru": " ",
   "t_ukr": " "
  },
  "detail": "",
  "detail_ua": "",
  "detail_number": "",
  "source_id": 0,
  "same_adr_comm": "",
  "confrm": "",
  "reg_date": "",
  "longt": 36.1737532263,
  "lati": 50.010819553,
  "FullNameUA": "вулиця Рельєфна, 22",
  "ChildsIds": []
 },
 {
  "id": 143891,
  "postcode": 61067,
  "number": 23,
  "suffix": "",
  "block": "",
  "streetid": 3771,
  "status_id": 1,
  "detail_type_index": 0,
  "AddressDetailType": {
   "id": 0,
   "t_ru": " ",
   "t_ukr": " "
  },
  "detail": "",
  "detail_ua": "",
  "detail_number": "",
  "source_id": 0,
  "same_adr_comm": "",
  "confrm": "",
  "reg_date": "",
  "longt": 36.1706951609,
  "lati": 50.0119573316,
  "FullNameUA": "вулиця Рельєфна, 23",
  "ChildsIds": []
 },
 {
  "id": 143892,
  "postcode": 61067,
  "number": 24,
  "suffix": "",
  "block": "",
  "streetid": 3771,
  "status_id": 1,
  "detail_type_index": 0,
  "AddressDetailType": {
   "id": 0,
   "t_ru": " ",
   "t_ukr": " "
  },
  "detail": "",
  "detail_ua": "",
  "detail_number": "",
  "source_id": 0,
  "same_adr_comm": "",
  "confrm": "",
  "reg_date": "",
  "longt": 36.1736500381,
  "lati": 50.0108811423,
  "FullNameUA": "вулиця Рельєфна, 24",
  "ChildsIds": []
 },
 {
  "id": 143893,
  "postcode": 61067,
  "number": 25,
  "suffix": "",
  "block": "",
  "streetid": 3771,
  "status_id": 1,
  "detail_type_index": 0,
  "AddressDetailType": {
   "id": 0,
   "t_ru": " ",
   "t_ukr": " "
  },
  "detail": "",
  "detail_ua": "",
  "detail_number": "",
  "source_id": 0,
  "same_adr_comm": "",
  "confrm": "",
  "reg_date": "",
  "longt": 36.1704383722,
  "lati": 50.0119835713,
  "FullNameUA": "вулиця Рельєфна, 25",
  "ChildsIds": []
 },
 {
  "id": 143894,
  "postcode": 61067,
  "number": 26,
  "suffix": "",
  "block": "",
  "streetid": 3771,
  "status_id": 1,
  "detail_type_index": 0,
  "AddressDetailType": {
   "id": 0,
   "t_ru": " ",
   "t_ukr": " "
  },
  "detail": "",
  "detail_ua": "",
  "detail_number": "",
  "source_id": 0,
  "same_adr_comm": "",
  "confrm": "",
  "reg_date": "",
  "longt": 36.1734052243,
  "lati": 50.0109648048,
  "FullNameUA": "вулиця Рельєфна, 26",
  "ChildsIds": []
 },
 {
  "id": 143895,
  "postcode": 61067,
  "number": 26,
  "suffix": "А",
  "block": "",
  "streetid": 3771,
  "status_id": 1,
  "detail_type_index": 0,
  "AddressDetailType": {
   "id": 0,
   "t_ru": " ",
   "t_ukr": " "
  },
  "detail": "",
  "detail_ua": "",
  "detail_number": "",
  "source_id": 0,
  "same_adr_comm": "",
  "confrm": "",
  "reg_date": "",
  "longt": 36.1732618895,
  "lati": 50.011045767,
  "FullNameUA": "вулиця Рельєфна, 26-А",
  "ChildsIds": []
 },
 {
  "id": 143896,
  "postcode": 61067,
  "number": 27,
  "suffix": "",
  "block": "",
  "streetid": 3771,
  "status_id": 1,
  "detail_type_index": 0,
  "AddressDetailType": {
   "id": 0,
   "t_ru": " ",
   "t_ukr": " "
  },
  "detail": "",
  "detail_ua": "",
  "detail_number": "",
  "source_id": 0,
  "same_adr_comm": "",
  "confrm": "",
  "reg_date": "",
  "longt": 36.1702713128,
  "lati": 50.0121799568,
  "FullNameUA": "вулиця Рельєфна, 27",
  "ChildsIds": []
 },
 {
  "id": 143898,
  "postcode": 61067,
  "number": 28,
  "suffix": "А",
  "block": "",
  "streetid": 3771,
  "status_id": 1,
  "detail_type_index": 0,
  "AddressDetailType": {
   "id": 0,
   "t_ru": " ",
   "t_ukr": " "
  },
  "detail": "",
  "detail_ua": "",
  "detail_number": "",
  "source_id": 0,
  "same_adr_comm": "",
  "confrm": "",
  "reg_date": "",
  "longt": 36.1730985447,
  "lati": 50.0111231487,
  "FullNameUA": "вулиця Рельєфна, 28-А",
  "ChildsIds": []
 },
 {
  "id": 143897,
  "postcode": 61067,
  "number": 28,
  "suffix": "",
  "block": "",
  "streetid": 3771,
  "status_id": 1,
  "detail_type_index": 0,
  "AddressDetailType": {
   "id": 0,
   "t_ru": " ",
   "t_ukr": " "
  },
  "detail": "",
  "detail_ua": "",
  "detail_number": "",
  "source_id": 0,
  "same_adr_comm": "",
  "confrm": "",
  "reg_date": "",
  "longt": 36.1729744342,
  "lati": 50.0112249868,
  "FullNameUA": "вулиця Рельєфна, 28",
  "ChildsIds": []
 },
 {
  "id": 143899,
  "postcode": 61067,
  "number": 30,
  "suffix": "",
  "block": "",
  "streetid": 3771,
  "status_id": 1,
  "detail_type_index": 0,
  "AddressDetailType": {
   "id": 0,
   "t_ru": " ",
   "t_ukr": " "
  },
  "detail": "",
  "detail_ua": "",
  "detail_number": "",
  "source_id": 0,
  "same_adr_comm": "",
  "confrm": "",
  "reg_date": "",
  "longt": 36.1728036662,
  "lati": 50.0113927378,
  "FullNameUA": "вулиця Рельєфна, 30",
  "ChildsIds": []
 },
 {
  "id": 143900,
  "postcode": 61067,
  "number": 32,
  "suffix": "",
  "block": "",
  "streetid": 3771,
  "status_id": 1,
  "detail_type_index": 0,
  "AddressDetailType": {
   "id": 0,
   "t_ru": " ",
   "t_ukr": " "
  },
  "detail": "",
  "detail_ua": "",
  "detail_number": "",
  "source_id": 0,
  "same_adr_comm": "",
  "confrm": "",
  "reg_date": "",
  "longt": 36.1725066829,
  "lati": 50.0114049571,
  "FullNameUA": "вулиця Рельєфна, 32",
  "ChildsIds": []
 },
 {
  "id": 143901,
  "postcode": 61067,
  "number": 34,
  "suffix": "",
  "block": "",
  "streetid": 3771,
  "status_id": 1,
  "detail_type_index": 0,
  "AddressDetailType": {
   "id": 0,
   "t_ru": " ",
   "t_ukr": " "
  },
  "detail": "",
  "detail_ua": "",
  "detail_number": "",
  "source_id": 0,
  "same_adr_comm": "",
  "confrm": "",
  "reg_date": "",
  "longt": 36.1717724981,
  "lati": 50.0118176262,
  "FullNameUA": "вулиця Рельєфна, 34",
  "ChildsIds": []
 },
 {
  "id": 143902,
  "postcode": 61067,
  "number": 36,
  "suffix": "",
  "block": "",
  "streetid": 3771,
  "status_id": 1,
  "detail_type_index": 0,
  "AddressDetailType": {
   "id": 0,
   "t_ru": " ",
   "t_ukr": " "
  },
  "detail": "",
  "detail_ua": "",
  "detail_number": "",
  "source_id": 0,
  "same_adr_comm": "",
  "confrm": "",
  "reg_date": "",
  "longt": 36.1714469591,
  "lati": 50.0119411864,
  "FullNameUA": "вулиця Рельєфна, 36",
  "ChildsIds": []
 },
 {
  "id": 143903,
  "postcode": 61067,
  "number": 38,
  "suffix": "",
  "block": "",
  "streetid": 3771,
  "status_id": 1,
  "detail_type_index": 0,
  "AddressDetailType": {
   "id": 0,
   "t_ru": " ",
   "t_ukr": " "
  },
  "detail": "",
  "detail_ua": "",
  "detail_number": "",
  "source_id": 0,
  "same_adr_comm": "",
  "confrm": "",
  "reg_date": "",
  "longt": 36.1712747908,
  "lati": 50.0120317131,
  "FullNameUA": "вулиця Рельєфна, 38",
  "ChildsIds": []
 },
 {
  "id": 143904,
  "postcode": 61067,
  "number": 40,
  "suffix": "",
  "block": "",
  "streetid": 3771,
  "status_id": 1,
  "detail_type_index": 0,
  "AddressDetailType": {
   "id": 0,
   "t_ru": " ",
   "t_ukr": " "
  },
  "detail": "",
  "detail_ua": "",
  "detail_number": "",
  "source_id": 0,
  "same_adr_comm": "",
  "confrm": "",
  "reg_date": "",
  "longt": 36.1711005256,
  "lati": 50.0121254416,
  "FullNameUA": "вулиця Рельєфна, 40",
  "ChildsIds": []
 },
 {
  "id": 143905,
  "postcode": 61067,
  "number": 42,
  "suffix": "",
  "block": "",
  "streetid": 3771,
  "status_id": 1,
  "detail_type_index": 0,
  "AddressDetailType": {
   "id": 0,
   "t_ru": " ",
   "t_ukr": " "
  },
  "detail": "",
  "detail_ua": "",
  "detail_number": "",
  "source_id": 0,
  "same_adr_comm": "",
  "confrm": "",
  "reg_date": "",
  "longt": 36.170943567,
  "lati": 50.0122021222,
  "FullNameUA": "вулиця Рельєфна, 42",
  "ChildsIds": []
 },
 {
  "id": 143906,
  "postcode": 61067,
  "number": 44,
  "suffix": "",
  "block": "",
  "streetid": 3771,
  "status_id": 1,
  "detail_type_index": 0,
  "AddressDetailType": {
   "id": 0,
   "t_ru": " ",
   "t_ukr": " "
  },
  "detail": "",
  "detail_ua": "",
  "detail_number": "",
  "source_id": 0,
  "same_adr_comm": "",
  "confrm": "",
  "reg_date": "",
  "longt": 36.1708330099,
  "lati": 50.0122507024,
  "FullNameUA": "вулиця Рельєфна, 44",
  "ChildsIds": []
 },
 {
  "id": 143907,
  "postcode": 61067,
  "number": 46,
  "suffix": "",
  "block": "",
  "streetid": 3771,
  "status_id": 1,
  "detail_type_index": 0,
  "AddressDetailType": {
   "id": 0,
   "t_ru": " ",
   "t_ukr": " "
  },
  "detail": "",
  "detail_ua": "",
  "detail_number": "",
  "source_id": 0,
  "same_adr_comm": "",
  "confrm": "",
  "reg_date": "",
  "longt": 36.1706068008,
  "lati": 50.0123549605,
  "FullNameUA": "вулиця Рельєфна, 46",
  "ChildsIds": []
 },
 {
  "id": 143908,
  "postcode": 61067,
  "number": 48,
  "suffix": "",
  "block": "",
  "streetid": 3771,
  "status_id": 1,
  "detail_type_index": 0,
  "AddressDetailType": {
   "id": 0,
   "t_ru": " ",
   "t_ukr": " "
  },
  "detail": "",
  "detail_ua": "",
  "detail_number": "",
  "source_id": 0,
  "same_adr_comm": "",
  "confrm": "",
  "reg_date": "",
  "longt": 36.1703509837,
  "lati": 50.0124579277,
  "FullNameUA": "вулиця Рельєфна, 48",
  "ChildsIds": []
 }
]