[
 {
  "id": 166241,
  "postcode": 61109,
  "number": 2,
  "suffix": "",
  "block": "",
  "streetid": 4156,
  "status_id": 1,
  "detail_type_index": 0,
  "AddressDetailType": {
   "id": 0,
   "t_ru": " ",
   "t_ukr": " "
  },
  "detail": "",
  "detail_ua": "",
  "detail_number": "",
  "source_id": 0,
  "same_adr_comm": "",
  "confrm": "",
  "reg_date": "",
  "longt": 36.202771468200005,
  "lati": 49.924077447900004,
  "FullNameUA": "провулок Трипільський, 2"
 },
 {
  "id": 166242,
  "postcode": 61109,
  "number": 4,
  "suffix": "",
  "block": "",
  "streetid": 4156,
  "status_id": 1,
  "detail_type_index": 0,
  "AddressDetailType": {
   "id": 0,
   "t_ru": " ",
   "t_ukr": " "
  },
  "detail": "",
  "detail_ua": "",
  "detail_number": "",
  "source_id": 0,
  "same_adr_comm": "",
  "confrm": "градархив",
  "reg_date": "",
  "longt": 36.203077286500005,
  "lati": 49.924156324,
  "FullNameUA": "провулок Трипільський, 4"
 },
 {
  "id": 166243,
  "postcode": 61109,
  "number": 6,
  "suffix": "",
  "block": "",
  "streetid": 4156,
  "status_id": 1,
  "detail_type_index": 0,
  "AddressDetailType": {
   "id": 0,
   "t_ru": " ",
   "t_ukr": " "
  },
  "detail": "",
  "detail_ua": "",
  "detail_number": "",
  "source_id": 0,
  "same_adr_comm": "",
  "confrm": "",
  "reg_date": "",
  "longt": 36.203713128400004,
  "lati": 49.9242804657,
  "FullNameUA": "провулок Трипільський, 6"
 },
 {
  "id": 166244,
  "postcode": 61109,
  "number": 8,
  "suffix": "",
  "block": "",
  "streetid": 4156,
  "status_id": 1,
  "detail_type_index": 0,
  "AddressDetailType": {
   "id": 0,
   "t_ru": " ",
   "t_ukr": " "
  },
  "detail": "",
  "detail_ua": "",
  "detail_number": "",
  "source_id": 0,
  "same_adr_comm": "",
  "confrm": "",
  "reg_date": "",
  "longt": 36.2037462393,
  "lati": 49.924517064300005,
  "FullNameUA": "провулок Трипільський, 8"
 },
 {
  "id": 166245,
  "postcode": 61109,
  "number": 10,
  "suffix": "",
  "block": "",
  "streetid": 4156,
  "status_id": 1,
  "detail_type_index": 0,
  "AddressDetailType": {
   "id": 0,
   "t_ru": " ",
   "t_ukr": " "
  },
  "detail": "",
  "detail_ua": "",
  "detail_number": "",
  "source_id": 0,
  "same_adr_comm": "",
  "confrm": "",
  "reg_date": "",
  "longt": 36.204229601,
  "lati": 49.9245496089,
  "FullNameUA": "провулок Трипільський, 10"
 }
]