[
 {
  "id": 157776,
  "postcode": 61071,
  "number": 1,
  "suffix": "",
  "block": "",
  "streetid": 4563,
  "status_id": 1,
  "detail_type_index": 0,
  "AddressDetailType": {
   "id": 0,
   "t_ru": " ",
   "t_ukr": " "
  },
  "detail": "",
  "detail_ua": "",
  "detail_number": "",
  "source_id": 0,
  "same_adr_comm": "",
  "confrm": "",
  "reg_date": "",
  "longt": 36.1900951964,
  "lati": 49.9262810201,
  "FullNameUA": "в'їзд Тираспольський, 1",
  "ChildsIds": []
 },
 {
  "id": 157777,
  "postcode": 61071,
  "number": 2,
  "suffix": "",
  "block": "",
  "streetid": 4563,
  "status_id": 1,
  "detail_type_index": 0,
  "AddressDetailType": {
   "id": 0,
   "t_ru": " ",
   "t_ukr": " "
  },
  "detail": "",
  "detail_ua": "",
  "detail_number": "",
  "source_id": 0,
  "same_adr_comm": "",
  "confrm": "",
  "reg_date": "",
  "longt": 36.1904758582,
  "lati": 49.9262216261,
  "FullNameUA": "в'їзд Тираспольський, 2",
  "ChildsIds": []
 },
 {
  "id": 157778,
  "postcode": 61071,
  "number": 4,
  "suffix": "",
  "block": "",
  "streetid": 4563,
  "status_id": 1,
  "detail_type_index": 0,
  "AddressDetailType": {
   "id": 0,
   "t_ru": " ",
   "t_ukr": " "
  },
  "detail": "",
  "detail_ua": "",
  "detail_number": "",
  "source_id": 0,
  "same_adr_comm": "",
  "confrm": "",
  "reg_date": "",
  "longt": 36.1906500381,
  "lati": 49.9264181773,
  "FullNameUA": "в'їзд Тираспольський, 4",
  "ChildsIds": []
 },
 {
  "id": 177428,
  "postcode": 61071,
  "number": 5,
  "suffix": "",
  "block": "",
  "streetid": 4563,
  "status_id": 1,
  "detail_type_index": 0,
  "AddressDetailType": {
   "id": 0,
   "t_ru": " ",
   "t_ukr": " "
  },
  "detail": "",
  "detail_ua": "",
  "detail_number": "",
  "source_id": 0,
  "same_adr_comm": "",
  "confrm": "градархив",
  "reg_date": "",
  "longt": 36.1902358155,
  "lati": 49.9265366859,
  "FullNameUA": "в'їзд Тираспольський, 5",
  "ChildsIds": []
 },
 {
  "id": 157779,
  "postcode": 61071,
  "number": 6,
  "suffix": "",
  "block": "",
  "streetid": 4563,
  "status_id": 1,
  "detail_type_index": 0,
  "AddressDetailType": {
   "id": 0,
   "t_ru": " ",
   "t_ukr": " "
  },
  "detail": "",
  "detail_ua": "",
  "detail_number": "",
  "source_id": 0,
  "same_adr_comm": "",
  "confrm": "",
  "reg_date": "",
  "longt": 36.1908730571,
  "lati": 49.9265837818,
  "FullNameUA": "в'їзд Тираспольський, 6",
  "ChildsIds": []
 },
 {
  "id": 157780,
  "postcode": 61071,
  "number": 7,
  "suffix": "",
  "block": "",
  "streetid": 4563,
  "status_id": 1,
  "detail_type_index": 0,
  "AddressDetailType": {
   "id": 0,
   "t_ru": " ",
   "t_ukr": " "
  },
  "detail": "",
  "detail_ua": "",
  "detail_number": "",
  "source_id": 0,
  "same_adr_comm": "",
  "confrm": "",
  "reg_date": "",
  "longt": 36.1904303377,
  "lati": 49.9268019696,
  "FullNameUA": "в'їзд Тираспольський, 7",
  "ChildsIds": []
 },
 {
  "id": 157781,
  "postcode": 61071,
  "number": 8,
  "suffix": "",
  "block": "",
  "streetid": 4563,
  "status_id": 1,
  "detail_type_index": 0,
  "AddressDetailType": {
   "id": 0,
   "t_ru": " ",
   "t_ukr": " "
  },
  "detail": "",
  "detail_ua": "",
  "detail_number": "",
  "source_id": 0,
  "same_adr_comm": "",
  "confrm": "градархив",
  "reg_date": "",
  "longt": 36.1909658886,
  "lati": 49.9268303708,
  "FullNameUA": "в'їзд Тираспольський, 8",
  "ChildsIds": []
 },
 {
  "id": 157782,
  "postcode": 61071,
  "number": 9,
  "suffix": "",
  "block": "",
  "streetid": 4563,
  "status_id": 1,
  "detail_type_index": 0,
  "AddressDetailType": {
   "id": 0,
   "t_ru": " ",
   "t_ukr": " "
  },
  "detail": "",
  "detail_ua": "",
  "detail_number": "",
  "source_id": 0,
  "same_adr_comm": "",
  "confrm": "",
  "reg_date": "",
  "longt": 36.1904641692,
  "lati": 49.9269717562,
  "FullNameUA": "в'їзд Тираспольський, 9",
  "ChildsIds": []
 },
 {
  "id": 157783,
  "postcode": 61071,
  "number": 10,
  "suffix": "",
  "block": "",
  "streetid": 4563,
  "status_id": 1,
  "detail_type_index": 0,
  "AddressDetailType": {
   "id": 0,
   "t_ru": " ",
   "t_ukr": " "
  },
  "detail": "",
  "detail_ua": "",
  "detail_number": "",
  "source_id": 0,
  "same_adr_comm": "",
  "confrm": "",
  "reg_date": "",
  "longt": 36.1912422859,
  "lati": 49.927316916,
  "FullNameUA": "в'їзд Тираспольський, 10",
  "ChildsIds": []
 }
]