[
 {
  "id": 130953,
  "postcode": 61013,
  "number": 1,
  "suffix": "А",
  "block": "",
  "streetid": 4593,
  "status_id": 1,
  "detail_type_index": 1,
  "AddressDetailType": {
   "id": 1,
   "t_ru": "участок",
   "t_ukr": "ділянка"
  },
  "detail": "участок № ",
  "detail_ua": "ділянка № ",
  "detail_number": "102",
  "source_id": 0,
  "same_adr_comm": "",
  "confrm": "градархив",
  "reg_date": "",
  "longt": 36.276721667000004,
  "lati": 50.0165530875,
  "FullNameUA": "в'їзд Омський, 1-А, ділянка № 102"
 },
 {
  "id": 130947,
  "postcode": 61013,
  "number": 1,
  "suffix": "А",
  "block": "",
  "streetid": 4593,
  "status_id": 1,
  "detail_type_index": 1,
  "AddressDetailType": {
   "id": 1,
   "t_ru": "участок",
   "t_ukr": "ділянка"
  },
  "detail": "участок № ",
  "detail_ua": "ділянка № ",
  "detail_number": "23",
  "source_id": 0,
  "same_adr_comm": "",
  "confrm": "градархив",
  "reg_date": "",
  "longt": 36.2736760306,
  "lati": 50.0178735623,
  "FullNameUA": "в'їзд Омський, 1-А, ділянка № 23"
 },
 {
  "id": 130948,
  "postcode": 61013,
  "number": 1,
  "suffix": "А",
  "block": "",
  "streetid": 4593,
  "status_id": 1,
  "detail_type_index": 1,
  "AddressDetailType": {
   "id": 1,
   "t_ru": "участок",
   "t_ukr": "ділянка"
  },
  "detail": "участок № ",
  "detail_ua": "ділянка № ",
  "detail_number": "26",
  "source_id": 0,
  "same_adr_comm": "",
  "confrm": "градархив",
  "reg_date": "",
  "longt": 36.2746085319,
  "lati": 50.0182243613,
  "FullNameUA": "в'їзд Омський, 1-А, ділянка № 26"
 },
 {
  "id": 130954,
  "postcode": 61013,
  "number": 1,
  "suffix": "А",
  "block": "",
  "streetid": 4593,
  "status_id": 1,
  "detail_type_index": 1,
  "AddressDetailType": {
   "id": 1,
   "t_ru": "участок",
   "t_ukr": "ділянка"
  },
  "detail": "участок № ",
  "detail_ua": "ділянка № ",
  "detail_number": "405",
  "source_id": 0,
  "same_adr_comm": "",
  "confrm": "градархив",
  "reg_date": "",
  "longt": 36.2750271485,
  "lati": 50.0189955034,
  "FullNameUA": "в'їзд Омський, 1-А, ділянка № 405"
 },
 {
  "id": 130955,
  "postcode": 61013,
  "number": 1,
  "suffix": "А",
  "block": "",
  "streetid": 4593,
  "status_id": 1,
  "detail_type_index": 1,
  "AddressDetailType": {
   "id": 1,
   "t_ru": "участок",
   "t_ukr": "ділянка"
  },
  "detail": "участок № ",
  "detail_ua": "ділянка № ",
  "detail_number": "407",
  "source_id": 0,
  "same_adr_comm": "",
  "confrm": "градархив",
  "reg_date": "",
  "longt": 36.274982921500005,
  "lati": 50.0187968532,
  "FullNameUA": "в'їзд Омський, 1-А, ділянка № 407"
 },
 {
  "id": 130949,
  "postcode": 61013,
  "number": 1,
  "suffix": "А",
  "block": "",
  "streetid": 4593,
  "status_id": 1,
  "detail_type_index": 1,
  "AddressDetailType": {
   "id": 1,
   "t_ru": "участок",
   "t_ukr": "ділянка"
  },
  "detail": "участок № ",
  "detail_ua": "ділянка № ",
  "detail_number": "53",
  "source_id": 0,
  "same_adr_comm": "",
  "confrm": "градархив",
  "reg_date": "",
  "longt": 36.275630898500005,
  "lati": 50.0165723357,
  "FullNameUA": "в'їзд Омський, 1-А, ділянка № 53"
 },
 {
  "id": 130950,
  "postcode": 61013,
  "number": 1,
  "suffix": "А",
  "block": "",
  "streetid": 4593,
  "status_id": 1,
  "detail_type_index": 1,
  "AddressDetailType": {
   "id": 1,
   "t_ru": "участок",
   "t_ukr": "ділянка"
  },
  "detail": "участок № ",
  "detail_ua": "ділянка № ",
  "detail_number": "57",
  "source_id": 0,
  "same_adr_comm": "",
  "confrm": "градархив",
  "reg_date": "",
  "longt": 36.2762861844,
  "lati": 50.016254407699996,
  "FullNameUA": "в'їзд Омський, 1-А, ділянка № 57"
 },
 {
  "id": 130951,
  "postcode": 61013,
  "number": 1,
  "suffix": "А",
  "block": "",
  "streetid": 4593,
  "status_id": 1,
  "detail_type_index": 1,
  "AddressDetailType": {
   "id": 1,
   "t_ru": "участок",
   "t_ukr": "ділянка"
  },
  "detail": "участок № ",
  "detail_ua": "ділянка № ",
  "detail_number": "76",
  "source_id": 0,
  "same_adr_comm": "",
  "confrm": "градархив",
  "reg_date": "",
  "longt": 36.2756817251,
  "lati": 50.0181423561,
  "FullNameUA": "в'їзд Омський, 1-А, ділянка № 76"
 },
 {
  "id": 130952,
  "postcode": 61013,
  "number": 1,
  "suffix": "А",
  "block": "",
  "streetid": 4593,
  "status_id": 1,
  "detail_type_index": 1,
  "AddressDetailType": {
   "id": 1,
   "t_ru": "участок",
   "t_ukr": "ділянка"
  },
  "detail": "участок № ",
  "detail_ua": "ділянка № ",
  "detail_number": "93",
  "source_id": 0,
  "same_adr_comm": "",
  "confrm": "градархив",
  "reg_date": "",
  "longt": 36.276183651800004,
  "lati": 50.017270192,
  "FullNameUA": "в'їзд Омський, 1-А, ділянка № 93"
 }
]