[
 {
  "id": 121897,
  "postcode": 61033,
  "number": 3,
  "suffix": "",
  "block": "",
  "streetid": 2426,
  "status_id": 1,
  "detail_type_index": 0,
  "AddressDetailType": {
   "id": 0,
   "t_ru": " ",
   "t_ukr": " "
  },
  "detail": "",
  "detail_ua": "",
  "detail_number": "",
  "source_id": 0,
  "same_adr_comm": "",
  "confrm": "фото гугл-карта",
  "reg_date": "",
  "longt": 36.2860264723,
  "lati": 50.0061686114,
  "FullNameUA": "провулок Герасимівський, 3"
 },
 {
  "id": 178509,
  "postcode": 61033,
  "number": 3,
  "suffix": "Б",
  "block": "",
  "streetid": 2426,
  "status_id": 1,
  "detail_type_index": 0,
  "AddressDetailType": {
   "id": 0,
   "t_ru": " ",
   "t_ukr": " "
  },
  "detail": "",
  "detail_ua": "",
  "detail_number": "",
  "source_id": 0,
  "same_adr_comm": "",
  "confrm": "фото гугл-карта",
  "reg_date": "",
  "longt": 36.2859344337,
  "lati": 50.005896478,
  "FullNameUA": "провулок Герасимівський, 3-Б"
 },
 {
  "id": 178510,
  "postcode": 61033,
  "number": 3,
  "suffix": "А",
  "block": "",
  "streetid": 2426,
  "status_id": 1,
  "detail_type_index": 0,
  "AddressDetailType": {
   "id": 0,
   "t_ru": " ",
   "t_ukr": " "
  },
  "detail": "",
  "detail_ua": "",
  "detail_number": "",
  "source_id": 0,
  "same_adr_comm": "",
  "confrm": "карта М1:2000",
  "reg_date": "",
  "longt": 36.2858526032,
  "lati": 50.0057896385,
  "FullNameUA": "провулок Герасимівський, 3-А"
 },
 {
  "id": 121898,
  "postcode": 61033,
  "number": 4,
  "suffix": "",
  "block": "",
  "streetid": 2426,
  "status_id": 1,
  "detail_type_index": 0,
  "AddressDetailType": {
   "id": 0,
   "t_ru": " ",
   "t_ukr": " "
  },
  "detail": "",
  "detail_ua": "",
  "detail_number": "",
  "source_id": 0,
  "same_adr_comm": "",
  "confrm": "",
  "reg_date": "",
  "longt": 36.28645755,
  "lati": 50.0061372969,
  "FullNameUA": "провулок Герасимівський, 4"
 },
 {
  "id": 121899,
  "postcode": 61033,
  "number": 6,
  "suffix": "",
  "block": "",
  "streetid": 2426,
  "status_id": 1,
  "detail_type_index": 0,
  "AddressDetailType": {
   "id": 0,
   "t_ru": " ",
   "t_ukr": " "
  },
  "detail": "",
  "detail_ua": "",
  "detail_number": "",
  "source_id": 0,
  "same_adr_comm": "",
  "confrm": "",
  "reg_date": "",
  "longt": 36.286498491,
  "lati": 50.0063521268,
  "FullNameUA": "провулок Герасимівський, 6"
 },
 {
  "id": 121900,
  "postcode": 61033,
  "number": 7,
  "suffix": "",
  "block": "",
  "streetid": 2426,
  "status_id": 1,
  "detail_type_index": 0,
  "AddressDetailType": {
   "id": 0,
   "t_ru": " ",
   "t_ukr": " "
  },
  "detail": "",
  "detail_ua": "",
  "detail_number": "",
  "source_id": 0,
  "same_adr_comm": "",
  "confrm": "",
  "reg_date": "",
  "longt": 36.286039515,
  "lati": 50.0063936529,
  "FullNameUA": "провулок Герасимівський, 7"
 },
 {
  "id": 121901,
  "postcode": 61033,
  "number": 8,
  "suffix": "",
  "block": "",
  "streetid": 2426,
  "status_id": 1,
  "detail_type_index": 0,
  "AddressDetailType": {
   "id": 0,
   "t_ru": " ",
   "t_ukr": " "
  },
  "detail": "",
  "detail_ua": "",
  "detail_number": "",
  "source_id": 0,
  "same_adr_comm": "",
  "confrm": "",
  "reg_date": "",
  "longt": 36.2865543189,
  "lati": 50.0066081067,
  "FullNameUA": "провулок Герасимівський, 8"
 },
 {
  "id": 121903,
  "postcode": 61033,
  "number": 8,
  "suffix": "Б",
  "block": "",
  "streetid": 2426,
  "status_id": 1,
  "detail_type_index": 0,
  "AddressDetailType": {
   "id": 0,
   "t_ru": " ",
   "t_ukr": " "
  },
  "detail": "",
  "detail_ua": "",
  "detail_number": "",
  "source_id": 0,
  "same_adr_comm": "",
  "confrm": "",
  "reg_date": "",
  "longt": 36.2868398483,
  "lati": 50.0065763644,
  "FullNameUA": "провулок Герасимівський, 8-Б"
 },
 {
  "id": 121902,
  "postcode": 61033,
  "number": 8,
  "suffix": "А",
  "block": "",
  "streetid": 2426,
  "status_id": 1,
  "detail_type_index": 0,
  "AddressDetailType": {
   "id": 0,
   "t_ru": " ",
   "t_ukr": " "
  },
  "detail": "",
  "detail_ua": "",
  "detail_number": "",
  "source_id": 0,
  "same_adr_comm": "",
  "confrm": "",
  "reg_date": "",
  "longt": 36.2867699417,
  "lati": 50.0067401293,
  "FullNameUA": "провулок Герасимівський, 8-А"
 },
 {
  "id": 121904,
  "postcode": 61033,
  "number": 9,
  "suffix": "",
  "block": "",
  "streetid": 2426,
  "status_id": 1,
  "detail_type_index": 0,
  "AddressDetailType": {
   "id": 0,
   "t_ru": " ",
   "t_ukr": " "
  },
  "detail": "",
  "detail_ua": "",
  "detail_number": "",
  "source_id": 0,
  "same_adr_comm": "",
  "confrm": "",
  "reg_date": "",
  "longt": 36.2861324314,
  "lati": 50.0066574319,
  "FullNameUA": "провулок Герасимівський, 9"
 },
 {
  "id": 121905,
  "postcode": 61033,
  "number": 10,
  "suffix": "",
  "block": "",
  "streetid": 2426,
  "status_id": 1,
  "detail_type_index": 0,
  "AddressDetailType": {
   "id": 0,
   "t_ru": " ",
   "t_ukr": " "
  },
  "detail": "",
  "detail_ua": "",
  "detail_number": "",
  "source_id": 0,
  "same_adr_comm": "",
  "confrm": "",
  "reg_date": "",
  "longt": 36.2865908874,
  "lati": 50.0069225364,
  "FullNameUA": "провулок Герасимівський, 10"
 },
 {
  "id": 121906,
  "postcode": 61033,
  "number": 11,
  "suffix": "",
  "block": "",
  "streetid": 2426,
  "status_id": 1,
  "detail_type_index": 0,
  "AddressDetailType": {
   "id": 0,
   "t_ru": " ",
   "t_ukr": " "
  },
  "detail": "",
  "detail_ua": "",
  "detail_number": "",
  "source_id": 0,
  "same_adr_comm": "",
  "confrm": "",
  "reg_date": "",
  "longt": 36.286165495300004,
  "lati": 50.0068270087,
  "FullNameUA": "провулок Герасимівський, 11"
 },
 {
  "id": 121907,
  "postcode": 61033,
  "number": 11,
  "suffix": "А",
  "block": "",
  "streetid": 2426,
  "status_id": 1,
  "detail_type_index": 0,
  "AddressDetailType": {
   "id": 0,
   "t_ru": " ",
   "t_ukr": " "
  },
  "detail": "",
  "detail_ua": "",
  "detail_number": "",
  "source_id": 0,
  "same_adr_comm": "",
  "confrm": "",
  "reg_date": "",
  "longt": 36.2862601924,
  "lati": 50.0070474294,
  "FullNameUA": "провулок Герасимівський, 11-А"
 },
 {
  "id": 121908,
  "postcode": 61033,
  "number": 12,
  "suffix": "",
  "block": "",
  "streetid": 2426,
  "status_id": 1,
  "detail_type_index": 0,
  "AddressDetailType": {
   "id": 0,
   "t_ru": " ",
   "t_ukr": " "
  },
  "detail": "",
  "detail_ua": "",
  "detail_number": "",
  "source_id": 0,
  "same_adr_comm": "",
  "confrm": "",
  "reg_date": "",
  "longt": 36.2866495462,
  "lati": 50.0071092866,
  "FullNameUA": "провулок Герасимівський, 12"
 },
 {
  "id": 121909,
  "postcode": 61033,
  "number": 13,
  "suffix": "",
  "block": "",
  "streetid": 2426,
  "status_id": 1,
  "detail_type_index": 0,
  "AddressDetailType": {
   "id": 0,
   "t_ru": " ",
   "t_ukr": " "
  },
  "detail": "",
  "detail_ua": "",
  "detail_number": "",
  "source_id": 0,
  "same_adr_comm": "",
  "confrm": "",
  "reg_date": "",
  "longt": 36.2867621212,
  "lati": 50.0091794627,
  "FullNameUA": "провулок Герасимівський, 13"
 },
 {
  "id": 121910,
  "postcode": 61033,
  "number": 19,
  "suffix": "",
  "block": "",
  "streetid": 2426,
  "status_id": 1,
  "detail_type_index": 0,
  "AddressDetailType": {
   "id": 0,
   "t_ru": " ",
   "t_ukr": " "
  },
  "detail": "",
  "detail_ua": "",
  "detail_number": "",
  "source_id": 0,
  "same_adr_comm": "",
  "confrm": "",
  "reg_date": "",
  "longt": 36.286950312900004,
  "lati": 50.0099150805,
  "FullNameUA": "провулок Герасимівський, 19"
 },
 {
  "id": 121911,
  "postcode": 61033,
  "number": 20,
  "suffix": "/19",
  "block": "",
  "streetid": 2426,
  "status_id": 1,
  "detail_type_index": 0,
  "AddressDetailType": {
   "id": 0,
   "t_ru": " ",
   "t_ukr": " "
  },
  "detail": "",
  "detail_ua": "",
  "detail_number": "",
  "source_id": 0,
  "same_adr_comm": "",
  "confrm": "",
  "reg_date": "",
  "longt": 36.2868669087,
  "lati": 50.0083783393,
  "FullNameUA": "провулок Герасимівський, 20/19"
 },
 {
  "id": 121912,
  "postcode": 61033,
  "number": 21,
  "suffix": "",
  "block": "",
  "streetid": 2426,
  "status_id": 1,
  "detail_type_index": 0,
  "AddressDetailType": {
   "id": 0,
   "t_ru": " ",
   "t_ukr": " "
  },
  "detail": "",
  "detail_ua": "",
  "detail_number": "",
  "source_id": 0,
  "same_adr_comm": "",
  "confrm": "",
  "reg_date": "",
  "longt": 36.2869690173,
  "lati": 50.0100607798,
  "FullNameUA": "провулок Герасимівський, 21"
 },
 {
  "id": 121913,
  "postcode": 61033,
  "number": 22,
  "suffix": "",
  "block": "",
  "streetid": 2426,
  "status_id": 1,
  "detail_type_index": 0,
  "AddressDetailType": {
   "id": 0,
   "t_ru": " ",
   "t_ukr": " "
  },
  "detail": "",
  "detail_ua": "",
  "detail_number": "",
  "source_id": 0,
  "same_adr_comm": "",
  "confrm": "",
  "reg_date": "",
  "longt": 36.286951366400004,
  "lati": 50.0087659149,
  "FullNameUA": "провулок Герасимівський, 22"
 },
 {
  "id": 121914,
  "postcode": 61033,
  "number": 23,
  "suffix": "",
  "block": "",
  "streetid": 2426,
  "status_id": 1,
  "detail_type_index": 0,
  "AddressDetailType": {
   "id": 0,
   "t_ru": " ",
   "t_ukr": " "
  },
  "detail": "",
  "detail_ua": "",
  "detail_number": "",
  "source_id": 0,
  "same_adr_comm": "",
  "confrm": "",
  "reg_date": "",
  "longt": 36.2870046093,
  "lati": 50.010208046799995,
  "FullNameUA": "провулок Герасимівський, 23"
 },
 {
  "id": 121915,
  "postcode": 61033,
  "number": 24,
  "suffix": "",
  "block": "",
  "streetid": 2426,
  "status_id": 1,
  "detail_type_index": 0,
  "AddressDetailType": {
   "id": 0,
   "t_ru": " ",
   "t_ukr": " "
  },
  "detail": "",
  "detail_ua": "",
  "detail_number": "",
  "source_id": 0,
  "same_adr_comm": "",
  "confrm": "",
  "reg_date": "",
  "longt": 36.2869882505,
  "lati": 50.0089733303,
  "FullNameUA": "провулок Герасимівський, 24"
 },
 {
  "id": 121916,
  "postcode": 61033,
  "number": 26,
  "suffix": "",
  "block": "",
  "streetid": 2426,
  "status_id": 1,
  "detail_type_index": 0,
  "AddressDetailType": {
   "id": 0,
   "t_ru": " ",
   "t_ukr": " "
  },
  "detail": "",
  "detail_ua": "",
  "detail_number": "",
  "source_id": 0,
  "same_adr_comm": "",
  "confrm": "",
  "reg_date": "",
  "longt": 36.2870578234,
  "lati": 50.0091452402,
  "FullNameUA": "провулок Герасимівський, 26"
 },
 {
  "id": 121917,
  "postcode": 61033,
  "number": 32,
  "suffix": "",
  "block": "",
  "streetid": 2426,
  "status_id": 1,
  "detail_type_index": 0,
  "AddressDetailType": {
   "id": 0,
   "t_ru": " ",
   "t_ukr": " "
  },
  "detail": "",
  "detail_ua": "",
  "detail_number": "",
  "source_id": 0,
  "same_adr_comm": "",
  "confrm": "",
  "reg_date": "",
  "longt": 36.2872589236,
  "lati": 50.010103132,
  "FullNameUA": "провулок Герасимівський, 32"
 }
]